slsdt/__init__.py
slsdt/__version__.py
slsdt/reader_csv.py
slsdt/slsdt.py
slsdt/utils.py
slsdt/version.py
tests/__init__.py
slsdt-0.0.2.dist-info/LICENSE
slsdt-0.0.2.dist-info/METADATA
slsdt-0.0.2.dist-info/WHEEL
slsdt-0.0.2.dist-info/top_level.txt
slsdt-0.0.2.dist-info/RECORD
