Metadata-Version: 2.1
Name: slsdt
Version: 0.0.2
Summary: Oblique decision tree using the LAHC heuristic. 
Home-page: https://github.com/jhonatangs/slsdt
Author: Souza, J.G. and Santos, H.G.
Author-email: jhonatan.souza@aluno.ufop.edu.br
License: EPL-2.0
Keywords: Oblique Decision Tree,Machine Learning,Classification,Heuristic,Optimization
Platform: UNKNOWN
Classifier: License :: OSI Approved :: Eclipse Public License 2.0 (EPL-2.0)
Classifier: Operating System :: OS Independent
Classifier: Programming Language :: Python :: 3
Classifier: Topic :: Scientific/Engineering :: Artificial Intelligence
Classifier: Topic :: Software Development :: Libraries
Requires-Python: >3.5.0
Requires-Dist: numpy
Requires-Dist: pandas
Requires-Dist: numba
Requires-Dist: scikit-learn
